ctxcore/__init__.py
ctxcore/ctdb.py
ctxcore/datatypes.py
ctxcore/genesig.py
ctxcore/recovery.py
ctxcore/rnkdb.py
resources/__init__.py
resources/delineations/__init__.py
resources/delineations/hg19-limited-upstream10000-tss-downstream10000-full-transcript.bed.gz
resources/delineations/hg19-limited-upstream500.bed.gz
resources/delineations/hg19-limited-upstream5000-tss-downstream5000-full-transcript.bed.gz
resources/tests/__init__.py
resources/tests/c6.all.v6.1.symbols.gmt
resources/tests/hg19-tss-centered-10kb-10species.mc9nr.genes_vs_motifs.rankings.feather
resources/tests/hg19-tss-centered-5kb-10species.mc9nr.db
ctxcore-0.2.0.dist-info/LICENSE.txt
ctxcore-0.2.0.dist-info/METADATA
ctxcore-0.2.0.dist-info/WHEEL
ctxcore-0.2.0.dist-info/top_level.txt
ctxcore-0.2.0.dist-info/RECORD
