Metadata-Version: 2.1
Name: ctxcore
Version: 0.2.0
Summary: Core functions for pycisTarget and the SCENIC tool suite
Home-page: https://github.com/aertslab/ctxcore
Author: Bram Van de Sande, Gert Hulselmans
Maintainer: Gert Hulselmans
Maintainer-email: gert.hulselmans@kuleuven.be
License: GNU General Public License v3
Keywords: ctxcore,cisTarget,pycisTarget,SCENIC,pySCENIC,pycisTopic
Platform: UNKNOWN
Classifier: Development Status :: 3 - Alpha
Classifier: Intended Audience :: Developers
Classifier: Programming Language :: Python :: 3.7
Classifier: Programming Language :: Python :: 3.8
Classifier: Programming Language :: Python :: 3.9
Classifier: Programming Language :: Python :: 3.10
Requires-Dist: cytoolz
Requires-Dist: frozendict
Requires-Dist: numba (>=0.51.2)
Requires-Dist: numpy
Requires-Dist: pandas (>=0.24)
Requires-Dist: pyarrow (>=8.0.0)
Requires-Dist: pyyaml
Requires-Dist: tqdm
